pykeigan/__init__.py
pykeigan/blecontroller.py
pykeigan/controller.py
pykeigan/usbcontroller.py
pykeigan/utils.py
pykeigan_motor-2.4.0.dist-info/METADATA
pykeigan_motor-2.4.0.dist-info/WHEEL
pykeigan_motor-2.4.0.dist-info/top_level.txt
pykeigan_motor-2.4.0.dist-info/RECORD
