Metadata-Version: 2.1
Name: pykeigan-motor
Version: 2.4.0
Summary: Python Library for Keigan Motors (v2)
Home-page: https://github.com/keigan-motor/pykeigan_motor
Author: Tomohiro Takata, Hiroshi Harada, Takashi Tokuda
Author-email: takata@innovotion.co.jp, harada@keigan.co.jp, tokuda@keigan.co.jp
License: MIT-LICENSE
Platform: UNKNOWN
Requires-Dist: pyserial
Provides-Extra: ble
Requires-Dist: bluepy ; extra == 'ble'
